tapp/__init__.py
tapp/anyio.py
tapp/applications.py
tapp/logger.py
tapp/utils.py
tapp/enums/__init__.py
tapp/enums/match.py
tapp/ext/tbot_api/__init__.py
tapp/ext/tbot_api/applications.py
tapp/ext/tbot_api/router.py
tapp/ext/tbot_api/filters/__init__.py
tapp/ext/tbot_api/filters/chat_type.py
tapp/ext/tbot_api/filters/content_types.py
tapp/ext/tbot_api/middleware/__init__.py
tapp/ext/tbot_api/middleware/context.py
tapp/filters/__init__.py
tapp/filters/data.py
tapp/filters/filter.py
tapp/middleware/__init__.py
tapp/middleware/base.py
tapp/middleware/exception.py
tapp/middleware/manager.py
tapp/routing/__init__.py
tapp/routing/route.py
tapp/routing/router.py
tapp/types/__init__.py
tapp/types/decorated.py
tapp/types/filter.py
tapp-1.2.dist-info/METADATA
tapp-1.2.dist-info/WHEEL
tapp-1.2.dist-info/licenses/LICENSE
tapp-1.2.dist-info/RECORD
