Metadata-Version: 2.1
Name: tapp
Version: 1.2
Summary: The library for management events
Author-email: t-me-api <seryumed@gmail.com>
License-File: LICENSE
Keywords: anyio,app,asyncio,events,events-library,telegram
Requires-Python: >=3.7
Requires-Dist: anyio~=3.6.2
Requires-Dist: magic-filter~=1.0.9
Requires-Dist: tbot-api~=1.0
Provides-Extra: dev
Requires-Dist: black~=23.1; extra == 'dev'
Requires-Dist: isort~=5.11; extra == 'dev'
Requires-Dist: ruff~=0.0.246; extra == 'dev'
Provides-Extra: test
Requires-Dist: pytest-asyncio~=0.20.3; extra == 'test'
Requires-Dist: pytest-cov~=4.0.0; extra == 'test'
Requires-Dist: pytest~=7.2.1; extra == 'test'
